{
  "title": "دل کے ہوتے ہوئے...",
  "slug": "دل-کے-ہوتے-ہوئے-70",
  "meter": "آزاد",
  "couplets": [
    {
      "line1": "دل کے ہوتے ہوئے آئینہ مقابل رکھا",
      "line2": "رہ گیادعویٰ یکتاؔئیِ قاتل رکھا"
    },
    {
      "line1": "وادیِ عشق میں ٹھہرا نہ کوئی میرے سوا",
      "line2": "قیس نے پائوں بھی رکھا تو بہ مشکل رکھا"
    },
    {
      "line1": "باتوں باتوں میں اڑالے گیا وہ دل میرا",
      "line2": "عالمِ ہوش میں کیا وہ مجھے غافل رکھا"
    },
    {
      "line1": "دل کو تسکین ہے تجھ  سے تو جگر کو ٹھنڈک",
      "line2": "ہم نے نام اس لئے تیرا مہِ کامل رکھا"
    },
    {
      "line1": "قصئہ درد و الم ان کو سنائوں کیوں کر",
      "line2": "ضعف نے بات بھی کرنے کے نہ قابل رکھا"
    },
    {
      "line1": "مرگئے پر بھی نہ ہم قید مصیبت سے چھٹے",
      "line2": "عمر بھر زلف نے پابند سلاسل رکھا"
    },
    {
      "line1": "آکے در تک بھی ترے تشنئہ دیدار رہا",
      "line2": "شور بختی ہی نے پیاسا لب ساحل رکھا"
    },
    {
      "line1": "اور مغرور نہ ہوجائے کہیں وہ خود بیں",
      "line2": "یار نے آئینہ پھر اپنے مقابل رکھا"
    },
    {
      "line1": "ہے مرے پیش نظرلیلیٰ مضمون کا جمال",
      "line2": "اس لئے قافیہ اس شعر میں محمل رکھا"
    },
    {
      "line1": "شکر ہے ہوگیا ارمانِ شہادت پورا",
      "line2": "جان کیا لی مرے نقاتل نے مرا دل رکھا"
    },
    {
      "line1": "گر پڑے اٹھتے ہی ہم اشک کی صورت یکتاؔ",
      "line2": "اک قدم بھی نہ سر ِ جادئہ منزل رکھا"
    }
  ]
}