{
  "title": "غضب رفتار ہے ،...",
  "slug": "غضب-رفتار-ہے-،-23",
  "meter": "آزاد",
  "couplets": [
    {
      "line1": "غضب رفتار ہے ، ظالم قیامت تیری ٹھوکر ہے",
      "line2": "یہاں ہر ہر روش سے صاف اک اندازِ محشر"
    },
    {
      "line1": "بلا سے راہ میں ہونے دو گر سدِسکندر ہے",
      "line2": "پہنچ ہی جائوں گا منزل پہ میں ہمت جو رہبر ہے"
    },
    {
      "line1": "اگر چشمِ حقیقت بیں سے نظارہ کرے کوئی",
      "line2": "زمین کا ذرہ ذرہ جلوئہ خالق کا مظہر ہے"
    },
    {
      "line1": "سنائوں قصہ بربدی کا شانہ دل کیا",
      "line2": "کبھی تھا یہ پرستاں ، اب تو اک اجڑا ہوا گھر ہے"
    },
    {
      "line1": "نہیں آسان ہے کچھ جھیلنا کڑیاں محبت کی",
      "line2": "وہی مائل ہو بتوں پر ، ہو کلیجہ جس کا پتھر ہے"
    },
    {
      "line1": "شرف حاصل ہے جس جو یار کی آئینہ داری کا",
      "line2": "حقیقت میںوہی اپنے نصیبے کا سکندر ہے"
    },
    {
      "line1": "کیا ہے بند جس نے دم فلک پر برق و باراں کا",
      "line2": "وہ مری آہِ سوزاں ہے وہ میرا دیدئہ تر ہے"
    },
    {
      "line1": "سفینہ آگیا یکتاؔ جو گردابِ حوادث میں",
      "line2": "یہی گردش زمانے کی، یہی قسمت کا چکر ہے"
    },
    {
      "line1": "خدا قائم رکھے یکتاؔ مرے استاد ہادی کو",
      "line2": "کہ باقی اب یہی تو اک سخن سنج و سخن ور ہے"
    }
  ]
}