{
  "title": "ہے گرمی الفت سے...",
  "slug": "ہے-گرمی-الفت-سے-14",
  "meter": "آزاد",
  "couplets": [
    {
      "line1": "ہے گرمی الفت سے دل آتش ، جگر آتش",
      "line2": "اب جائوں کدھر میں ، ادھر آتش، ادھر آتش"
    },
    {
      "line1": "ممکن نہیں دیکھے کوئی اس پردہ نشین کو",
      "line2": "موسٰی کو وظر آئی فقط اس طور پر آتش"
    },
    {
      "line1": "پائے نہ اماں جب مرے اشکوں سے زمیں پر",
      "line2": "کیوں اپنا بنائے نہ جہنم میں گھر آتش"
    },
    {
      "line1": "کیا حال کہوں دل کا ، کبھی کچھ ہے کبھی کچھ",
      "line2": "دن بھر ہے اگر آب تو ، ہے رات بھر آتش"
    },
    {
      "line1": "اعمال یہ اور بارشِ رحمت کی تمنا",
      "line2": "برسے نہ فلک سے کہیں وہ بے خبر آتش"
    },
    {
      "line1": "اظہارِ تمنا پہ ہوا آگ بگولہ",
      "line2": "آتا ہے نظر وہ بتِ بیداد گر آتش"
    },
    {
      "line1": "پیری میں بھڑکتی ہے ، جوانی کی دبی آگ",
      "line2": "سلگاتے ہیں ہر گھر میں بہ وقتِ سحر آتش"
    },
    {
      "line1": "آتش کدہ ہے جوش ، گل ولالہ سے گلشن",
      "line2": "ہے جلوہ فروز آج بہ رنگِ دگر آتش"
    },
    {
      "line1": "اس ترکِ پری  ورش کو تو ہے شوقِ سواری",
      "line2": "عشاق مگر رہتے ہیں سب نعل درآتش"
    },
    {
      "line1": "کب داغوں نے شعلہ کی حرارت نہ دکھائی",
      "line2": "کب خانئہ دل میں نہ ، لگی پر خطر آتش"
    },
    {
      "line1": "اشکوں سے زمیں تر ہے تو ، آہوں سے فلک خشک",
      "line2": "ہے زیرِ قدم آب تو ، بالائے سر آتش"
    },
    {
      "line1": "سب خانہ ہستی کے جلانے میں ہوئی صرف",
      "line2": "تھی سینئہ سوزاں میں بھری جس قدر آتش"
    },
    {
      "line1": "کیا گرمیِ رفتار ہے اس مہر کی یکتاؔ",
      "line2": "ہر ذرہ نظر آتا ہے سیماب بر آتش"
    },
    {
      "line1": "غزل",
      "line2": "جب تک نہ اپنی آہ کو نشتر کرے کوئی"
    },
    {
      "line1": "ممکن نہیں کہ دل میں ترے گھر کرے کوئی",
      "line2": "دردِ جگر کو تھاموں کہ رو کوں میں اشک کو"
    },
    {
      "line1": "دوکام ایکوقت میں کیوں کر کرے کوئی",
      "line2": "مانند شمع منھ سے کلیجہ نکل پڑے"
    },
    {
      "line1": "آہیں مری طرح سے جو شب بھر کرے کوئی",
      "line2": "اس بادشاہِ حسن نے چھنوائی مجھ سے خاک"
    },
    {
      "line1": "مفلس کسی کو یوں نہ تونگر کرے کوئی",
      "line2": "گھر سے مجھے جنوں نے نکالا ہے جس طرح"
    },
    {
      "line1": "یوں کھینچ کر کسی کو نہ باہر کرے کوئی",
      "line2": "آیا نہ وقتِ نزع میں یکتاؔ وہ سنگ دل"
    },
    {
      "line1": "اتنا بھی اپنے دل کو نہ پتھر کرے کوئی",
      "line2": "غزل"
    },
    {
      "line1": "بپا کر دے نہ فتنہ پھر یہ چرخ  پرفتن تازہ",
      "line2": "کیا ہے زلف و قد نے قصئہ دار و رسن تازہ"
    },
    {
      "line1": "نہ کوئی دوست باقی ہے نہ اب کوئی شناسا",
      "line2": "؁خبر لائے وطن سے کیا کوئی اہلِ وطن تازہ"
    },
    {
      "line1": "دلِ وحشی پہ میرے  ناوکِ ظلم و ستم چھوڑا",
      "line2": "نظر آیا نہ جب صیاد کو ، کوئی ہرن تازہ"
    },
    {
      "line1": "شہید جور قاتل ہوں ، یہی پہچان ہے میری",
      "line2": "رہ گا یشر تک لاشہ ، میرا زیر کفن  تازہ"
    },
    {
      "line1": "ہزاروں مردے جی اٹھے ، تری اک جنبشِ لب سے",
      "line2": "مگر چشمہ ہے آب ، زند گانی کا دہن تازہ"
    },
    {
      "line1": "نسیم صبح آتی ہے ترے کوچے سے رہ رہ کر",
      "line2": "ہوا کھائیں نہ کیوں ہر صبح مرغان چمن تازہ"
    },
    {
      "line1": "خزاں کے دن ہی اچھے ہیں ، غنیمت جانئیے ان کو",
      "line2": "جہاں فصلِ بہار آئی ہو ، دیوانہ پن تازہ"
    },
    {
      "line1": "بدل جائے گا نقشہ ان کی صورت کا جواں ہو کر",
      "line2": "نیا ابرو میں بل ہوگا ، جبیںپر اک شکن تازہ"
    },
    {
      "line1": "کھلے پھر پھول باغِ  دہر میں ، پھر فصلِ گل آئی",
      "line2": "ہوا جوشِ جنوں پھر ، پھر ہوئے داغِ کہن تازہ"
    },
    {
      "line1": "ملے فرصت اگر بھی ، غم شوز نہانی سے",
      "line2": "سنائے داستاں ہر رات شمع انجمن تازہ"
    },
    {
      "line1": "ترا ہر شعر یکتاؔ کام کرتا ہے مسیحا کا",
      "line2": "دلِ مردہ میں جاں آتی ہے سن سن کر سخن تازہ"
    },
    {
      "line1": "غزل",
      "line2": "لبِ دریا حباب کی باتیں"
    },
    {
      "line1": "ہیں ہوا اور آب کی باتیں",
      "line2": "وصل میں بھی کھلی نہ ان کی باتیں"
    },
    {
      "line1": "ہاں ہوئیں تو حجاب کی باتیں",
      "line2": "دل میں کیا ان کے ہے خدا جانے"
    },
    {
      "line1": "لب پہ تو ہیں عتاب کی باتیں",
      "line2": "شبِ ظلمت میں یاد آتی ہیں"
    },
    {
      "line1": "وہ شبِ ماہتاب ، کی باتیں",
      "line2": "کچھ سمجھ میں ذرا نہیں آتیں"
    },
    {
      "line1": "ِشیخ صاحب جناب کی باتیں",
      "line2": "ہجر میں آنکھ سے ٹپکتی ہیں"
    },
    {
      "line1": "خون بن کر شراب کی باتیں",
      "line2": "چشم ِ نرگس بھی بند ہو یکتاؔ"
    }
  ]
}